articulo/__init__.py
articulo/articulo.py
articulo/constants.py
articulo/exceptions.py
articulo/utils.py
articulo-0.5.1.dist-info/LICENSE
articulo-0.5.1.dist-info/METADATA
articulo-0.5.1.dist-info/WHEEL
articulo-0.5.1.dist-info/RECORD
