Metadata-Version: 2.1
Name: articulo
Version: 0.5.1
Summary: 
Author: Mikhail Ivanov
Author-email: ya.ivanov-m2014v@yandex.ru
Requires-Python: >=3.10,<4.0
Classifier: Programming Language :: Python :: 3
Classifier: Programming Language :: Python :: 3.10
Classifier: Programming Language :: Python :: 3.11
Requires-Dist: beautifulsoup4 (>=4.12.2,<5.0.0)
Requires-Dist: extruct (>=0.17.0,<0.18.0)
Requires-Dist: lxml (>=5.2.2,<6.0.0)
Requires-Dist: requests (>=2.31.0,<3.0.0)
Requires-Dist: validators (>=0.32.0,<0.33.0)
